api/__init__.py
api/auth.py
api/config.py
api/main.py
api/models.py
api/routes.py
api/schemas.py
api/_internal/__init__.py
api/_internal/database.py
api/_internal/store.py
sdk/__init__.py
sdk/client.py
sdk/config.py
sdk/decorators.py
sdk/middleware.py
sdk/types.py
sdk/_internal/__init__.py
sdk/_internal/run.py
sdk/_internal/step.py
sdk/_internal/transport.py
shared/__init__.py
shared/config.py
shared/types.py
xray_logger-0.1.1.dist-info/METADATA
xray_logger-0.1.1.dist-info/WHEEL
xray_logger-0.1.1.dist-info/RECORD
