Metadata-Version: 2.4
Name: xray-logger
Version: 0.1.1
Summary: Decision-level observability for ML/LLM pipelines
Author-email: Mohit Nagaraj <mohitnagaraj20@gmail.com>
License: MIT
Requires-Python: >=3.12
Requires-Dist: pydantic>=2.5
Requires-Dist: pyyaml>=6.0
Provides-Extra: all
Requires-Dist: aiosqlite>=0.20; extra == 'all'
Requires-Dist: asyncpg>=0.29; extra == 'all'
Requires-Dist: fastapi>=0.109; extra == 'all'
Requires-Dist: httpx>=0.27; extra == 'all'
Requires-Dist: mypy>=1.8; extra == 'all'
Requires-Dist: pytest-asyncio>=0.23; extra == 'all'
Requires-Dist: pytest>=8.0; extra == 'all'
Requires-Dist: respx>=0.21; extra == 'all'
Requires-Dist: ruff>=0.2; extra == 'all'
Requires-Dist: sqlalchemy[asyncio]>=2.0; extra == 'all'
Requires-Dist: starlette>=0.27; extra == 'all'
Requires-Dist: uvicorn>=0.27; extra == 'all'
Provides-Extra: api
Requires-Dist: aiosqlite>=0.20; extra == 'api'
Requires-Dist: asyncpg>=0.29; extra == 'api'
Requires-Dist: fastapi>=0.109; extra == 'api'
Requires-Dist: sqlalchemy[asyncio]>=2.0; extra == 'api'
Requires-Dist: uvicorn>=0.27; extra == 'api'
Provides-Extra: dev
Requires-Dist: mypy>=1.8; extra == 'dev'
Requires-Dist: pytest-asyncio>=0.23; extra == 'dev'
Requires-Dist: pytest>=8.0; extra == 'dev'
Requires-Dist: respx>=0.21; extra == 'dev'
Requires-Dist: ruff>=0.2; extra == 'dev'
Provides-Extra: sdk
Requires-Dist: httpx>=0.27; extra == 'sdk'
Requires-Dist: starlette>=0.27; extra == 'sdk'
